Metadata-Version: 2.1
Name: multipronto
Version: 0.0.0.1a0
Summary: Lightweight stream multiplexing
Home-page: https://www.antonioerusso.com/projects/multipronto/
Author: Antonio E. Russo
Author-email: aerusso@aerusso.net
License: APGLv3
Classifier: Development Status :: 1 - Planning
Classifier: Intended Audience :: Developers
Classifier: License :: OSI Approved :: GNU Affero General Public License v3
Classifier: Programming Language :: Python :: 3
Classifier: Topic :: Internet
Requires-Python: >=3.8
